{"type": "Feature", "id": 22117423, "properties": {"woe:id": 22117423, "woe:parent_id": 2151602, "woe:name": "Shanghai Stadium", "woe:placetype": 20, "woe:placetype_name": "POI", "woe:lang": "ENG", "iso:country": "CN", "meta:provider": ["geoplanet:7.5.1", "geoplanet:7.5.2", "geoplanet:7.6.0", "geoplanet:7.8.1", "geoplanet:7.9.0", "geoplanet:7.10.0", "geoplanet:8.0.0", "woeplanet:8.0.0"], "meta:indexed": "2020-08-21T03:30:43.844830", "meta:updated": "2020-08-22T01:57:48.402301", "woe:hierarchy": {"continent": 24865671, "country": 23424781, "town": 0, "planet": 1, "county": 26198093, "suburb": 0, "state": 12578012, "region": 0, "localadmin": 56043482}, "woe:timezone_id": 56043597, "woe:hash": "wtw37kdz2gsj", "woe:centroid": [121.435699, 31.18321], "geom:latitude": 31.18321, "geom:longitude": 121.435699, "geom:hash": "wtw37kdz2gsj", "woe:latitude": 31.18321, "geom:centroid": [121.435699, 31.18321], "woe:longitude": 121.435699, "woe:repo": "woeplanet-poi-cn"}, "geometry": {"coordinates": [121.435699, 31.18321], "type": "Point"}}