{"type": "Feature", "id": 22116052, "geometry": {"type": "Point", "coordinates": [116.390007, 39.898529]}, "properties": {"woe:id": 22116052, "woe:parent_id": 56043478, "woe:name": "Qianmen Station", "woe:placetype": 20, "woe:placetype_name": "POI", "woe:lang": "ENG", "iso:country": "CN", "meta:provider": ["geoplanet:7.3.1", "geoplanet:7.3.2", "geoplanet:7.4.0", "geoplanet:7.4.1", "geoplanet:7.5.1", "geoplanet:7.5.2", "geoplanet:7.6.0", "geoplanet:7.8.1", "geoplanet:7.9.0", "geoplanet:7.10.0", "geoplanet:8.0.0", "woeplanet:8.0.0"], "meta:indexed": "2020-08-20T20:57:52.073349", "meta:updated": "2020-10-14T12:05:21.422247", "woe:hierarchy": {"continent": 24865671, "country": 23424781, "town": 0, "planet": 1, "county": 12686916, "suburb": 0, "state": 12578011, "region": 0, "localadmin": 56043478}, "woe:timezone_id": 56043597, "woe:hash": "wx4fbx29g8zk", "woe:centroid": [116.390007, 39.898529], "geom:latitude": 39.898529, "geom:longitude": 116.390007, "geom:hash": "wx4fbx29g8zk", "woe:latitude": 39.898529, "geom:centroid": [116.390007, 39.898529], "woe:longitude": 116.390007, "woe:repo": "woeplanet-poi-cn", "geom:area": 0.0, "woe:scale": 19}}