{"type": "Feature", "id": 22116968, "geometry": {"type": "Point", "coordinates": [102.690048, 25.056259]}, "properties": {"woe:id": 22116968, "woe:parent_id": 2160693, "woe:name": "Ma yuan zhan Station", "woe:placetype": 20, "woe:placetype_name": "POI", "woe:lang": "ENG", "iso:country": "CN", "meta:provider": ["geoplanet:7.3.1", "geoplanet:7.3.2", "geoplanet:7.4.0", "geoplanet:7.4.1", "geoplanet:7.5.1", "geoplanet:7.5.2", "geoplanet:7.6.0", "geoplanet:7.8.1", "geoplanet:7.9.0", "geoplanet:7.10.0", "geoplanet:8.0.0", "woeplanet:8.0.0"], "meta:indexed": "2020-08-20T20:57:52.124211", "meta:updated": "2020-10-14T12:05:21.441760", "woe:hierarchy": {"continent": 24865671, "country": 23424781, "town": 0, "planet": 1, "county": 26198186, "suburb": 0, "state": 12578018, "region": 0, "localadmin": 12687505}, "woe:timezone_id": 56043593, "woe:hash": "wk3n8c2e791w", "woe:centroid": [102.690048, 25.056259], "geom:latitude": 25.056259, "geom:longitude": 102.690048, "geom:hash": "wk3n8c2e791w", "woe:latitude": 25.056259, "geom:centroid": [102.690048, 25.056259], "woe:longitude": 102.690048, "woe:repo": "woeplanet-poi-cn", "geom:area": 0.0, "woe:scale": 19}}