{"type": "Feature", "id": 22116021, "properties": {"woe:id": 22116021, "woe:parent_id": 56043477, "woe:name": "Nanlishi lu Station", "woe:placetype": 20, "woe:placetype_name": "POI", "woe:lang": "ENG", "iso:country": "CN", "meta:provider": ["geoplanet:7.3.1", "geoplanet:7.3.2", "geoplanet:7.4.0", "geoplanet:7.4.1", "geoplanet:7.5.1", "geoplanet:7.5.2", "geoplanet:7.6.0", "geoplanet:7.8.1", "geoplanet:7.9.0", "geoplanet:7.10.0", "geoplanet:8.0.0", "woeplanet:8.0.0"], "meta:indexed": "2020-08-20T20:57:52.072132", "meta:updated": "2020-08-22T01:57:48.362526", "woe:hierarchy": {"continent": 24865671, "country": 23424781, "town": 0, "planet": 1, "county": 12686916, "suburb": 0, "state": 12578011, "region": 0, "localadmin": 56043477}, "woe:timezone_id": 56043597, "woe:hash": "wx4ep2xjehw6", "woe:centroid": [116.343979, 39.906059], "geom:latitude": 39.906059, "geom:longitude": 116.343979, "geom:hash": "wx4ep2xjehw6", "woe:latitude": 39.906059, "geom:centroid": [116.343979, 39.906059], "woe:longitude": 116.343979, "woe:repo": "woeplanet-poi-cn"}, "geometry": {"coordinates": [116.343979, 39.906059], "type": "Point"}}