{"type": "Feature", "id": 22116661, "properties": {"woe:id": 22116661, "woe:parent_id": 20268995, "woe:name": "Huo che dong zhan Station", "woe:placetype": 20, "woe:placetype_name": "POI", "woe:lang": "ENG", "iso:country": "CN", "meta:provider": ["geoplanet:7.3.1", "geoplanet:7.3.2", "geoplanet:7.4.0", "geoplanet:7.4.1", "geoplanet:7.5.1", "geoplanet:7.5.2", "geoplanet:7.6.0", "geoplanet:7.8.1", "geoplanet:7.9.0", "geoplanet:7.10.0", "geoplanet:8.0.0", "woeplanet:8.0.0"], "meta:indexed": "2020-08-20T20:57:52.112507", "meta:updated": "2020-08-22T01:57:48.387186", "woe:hierarchy": {"continent": 24865671, "country": 23424781, "town": 0, "planet": 1, "county": 26198147, "suburb": 0, "state": 12577992, "region": 0, "localadmin": 12685402}, "woe:timezone_id": 56043597, "woe:hash": "wtmkr6krv1vp", "woe:centroid": [120.207474, 30.292021], "geom:latitude": 30.292021, "geom:longitude": 120.207474, "geom:hash": "wtmkr6krv1vp", "woe:latitude": 30.292021, "geom:centroid": [120.207474, 30.292021], "woe:longitude": 120.207474, "woe:repo": "woeplanet-poi-cn"}, "geometry": {"coordinates": [120.207474, 30.292021], "type": "Point"}}